newsdataapi/__init__.py
newsdataapi/constants.py
newsdataapi/helpers.py
newsdataapi/newsdataapi_client.py
newsdataapi/newsdataapi_exception.py
newsdataapi/utils.py
newsdataapi-0.1.29.dist-info/LICENSE
newsdataapi-0.1.29.dist-info/METADATA
newsdataapi-0.1.29.dist-info/WHEEL
newsdataapi-0.1.29.dist-info/top_level.txt
newsdataapi-0.1.29.dist-info/RECORD
