Metadata-Version: 2.1
Name: newsdataapi
Version: 0.1.29
Summary: Python library for newsdata client-API Call
Home-page: https://github.com/newsdataapi/python-client
Author: NewsData.io
Author-email: contact@newsdata.io
License: MIT
Keywords: news,news data
Platform: UNKNOWN
Classifier: Development Status :: 2 - Pre-Alpha
Classifier: Intended Audience :: Developers
Classifier: Intended Audience :: Customer Service
Classifier: License :: OSI Approved :: MIT License
Classifier: Programming Language :: Python :: 3
Classifier: Programming Language :: Python :: 3.5
Classifier: Programming Language :: Python :: 3.6
Classifier: Programming Language :: Python :: 3.7
Classifier: Programming Language :: Python :: 3.8
Classifier: Programming Language :: Python :: 3.9
Requires-Python: >=3.5
Requires-Dist: requests<3.0.0
